<?xml version="1.0" encoding="UTF-8"?>

<!DOCTYPE tiles-definitions PUBLIC
       "-//Apache Software Foundation//DTD Tiles Configuration 2.0//EN"
       "http://tiles.apache.org/dtds/tiles-config_2_0.dtd">
      
<tiles-definitions>
	
	<definition name="activityRecord/list" extends="master.page">	
		<put-attribute name="title" value="Lista de registro de actividades" />
		<put-attribute name="body" value="/views/activityRecord/list.jsp" />
	</definition>
	
	<definition name="activityRecord/edit" extends="master.page">	
		<put-attribute name="title" value="Editar registro de actividad" />
		<put-attribute name="body" value="/views/activityRecord/edit.jsp" />
	</definition>
	
</tiles-definitions>